<?xml version="1.0" encoding="utf-8" standalone="yes"?>
<ApplicationMetrics NAsm="4" NbSourceFiles="38" NbLinesOfCode="484" NbLinesOfComment="110" PercentageComment="18" NType="98" NClass="74" NAbstractClass="0" NInterface="17" NValueType="4" NExceptionType="0" NAttributeType="0" NDelegateType="17" NEnumType="3" NGenericMethodsDefinition="0" NGenericTypesDefinition="0" NILInstruction="3816" NMethods="457" NFields="228" NNamespaces="18" NThirdPartyAssemblies="8" NThirdPartyNamespaces="26" NThirdPartyTypes="119" NThirdPartyMethods="90" NThirdPartyFields="2" PercentCodeCoverage="0" PercentPublicType="70.41" PercentPublicMethod="88.4" PercentClassWithAtLeastOnePublicField="0">
  <PropertyOnInterface Occ="17" Avg="0.65" StdDev="0.84" MaxVal="3" MaxName="Poncho.ViewModels.ITrackListViewModel" />
  <MethodOnInterface Occ="17" Avg="4.24" StdDev="4.37" MaxVal="18" MaxName="SpotifyService.Interfaces.ISpotifyWrapper" />
  <ArgOnMethodOnInterface Occ="72" Avg="0.64" StdDev="0.58" MaxVal="2" MaxName="SpotifyService.Interfaces.IMusicServices.InitializeSession(String,String)" />
  <PublicPropertyOnClass Occ="74" Avg="0.34" StdDev="0.89" MaxVal="6" MaxName="SpotifyService.Cargo.SearchResult" />
  <PublicMethodOnClass Occ="74" Avg="4.49" StdDev="5.39" MaxVal="44" MaxName="SpotifyService.SpotifyWrapper" />
  <ArgOnPublicMethodOnClass Occ="332" Avg="0.87" StdDev="1.17" MaxVal="10" MaxName="SpotifyService.SpotifyWrapper.sp_search_create(IntPtr,Char[]&amp;,Int32,Int32,Int32,Int32,Int32,Int32,IntPtr,IntPtr)" />
  <ILInstructionInNonAbstractMethods Occ="385" Avg="9.91" StdDev="14.24" MaxVal="124" MaxName="SpotifyServiceTests.MusicServicesTests.SearchResultsRetrieved_ConstructsSearchResultCorrectly()" />
  <TypeWithTheMostILInstruction Occ="74" Avg="51.57" StdDev="79.33" MaxVal="469" MaxName="SpotifyServiceTests.MusicServicesTests" />
  <MethodCC Occ="385" Avg="1.04" StdDev="1.06" MaxVal="9" MaxName="Poncho.Views.LogInView.System.Windows.Markup.IComponentConnector.Connect(Int32,Object)" />
</ApplicationMetrics>